xomate/README.md
xomate/__init__.py
xomate/config.py
xomate/main.py
xomate/package_name.txt
xomate/requirements.txt
xomate/core/systems.py
xomate/ui/info.py
xomate/ui/prompts.py
xomate-0.0.13.dist-info/METADATA
xomate-0.0.13.dist-info/WHEEL
xomate-0.0.13.dist-info/entry_points.txt
xomate-0.0.13.dist-info/top_level.txt
xomate-0.0.13.dist-info/RECORD
