Metadata-Version: 2.1
Name: xomate
Version: 0.0.13
Summary: AgentMake AI MCP Servers - Easy setup of MCP servers running AgentMake AI agentic components.
Home-page: https://toolmate.ai
Author: Eliran Wong
Author-email: support@toolmate.ai
License: GNU General Public License (GPL)
Project-URL: Source, https://github.com/eliranwong/xomate
Project-URL: Tracker, https://github.com/eliranwong/xomate/issues
Project-URL: Documentation, https://github.com/eliranwong/xomate/wiki
Project-URL: Funding, https://www.paypal.me/toolmate
Keywords: mcp agent toolmate ai anthropic azure chatgpt cohere deepseek genai github googleai groq llamacpp mistral ollama openai vertexai xai
Classifier: Development Status :: 5 - Production/Stable
Classifier: Intended Audience :: End Users/Desktop
Classifier: Topic :: Utilities
Classifier: Topic :: Scientific/Engineering :: Artificial Intelligence
Classifier: Topic :: Software Development :: Build Tools
Classifier: License :: OSI Approved :: GNU General Public License v3 or later (GPLv3+)
Classifier: Programming Language :: Python :: 3.8
Classifier: Programming Language :: Python :: 3.9
Classifier: Programming Language :: Python :: 3.10
Classifier: Programming Language :: Python :: 3.11
Classifier: Programming Language :: Python :: 3.12
Requires-Python: >=3.8, <3.13
Requires-Dist: agentmake >=1.0.63
Requires-Dist: agentmakemcp >=0.0.8
Requires-Dist: alive-progress
Requires-Dist: fastmcp
Requires-Dist: rich
Provides-Extra: genai
Requires-Dist: google-genai >=1.25.0 ; extra == 'genai'
